{
	"$schema": "http://schema.management.azure.com/schemas/2015-01-01/deploymentTemplate.json#",
	"contentVersion": "1.0.0.0",
	"parameters": {
		"factoryName": {
			"type": "string",
			"metadata": "Data Factory name",
			"defaultValue": "class2503datafactory"
		}
	},
	"variables": {
		"factoryId": "[concat('Microsoft.DataFactory/factories/', parameters('factoryName'))]"
	},
	"resources": [
		{
			"name": "[concat(parameters('factoryName'), '/dataflow1')]",
			"type": "Microsoft.DataFactory/factories/dataflows",
			"apiVersion": "2018-06-01",
			"properties": {
				"type": "MappingDataFlow",
				"typeProperties": {
					"sources": [
						{
							"dataset": {
								"referenceName": "ds_duplcate",
								"type": "DatasetReference"
							},
							"name": "source1"
						}
					],
					"sinks": [
						{
							"dataset": {
								"referenceName": "ds_output",
								"type": "DatasetReference"
							},
							"name": "sink1"
						}
					],
					"transformations": [
						{
							"name": "aggregate1"
						},
						{
							"name": "select1"
						},
						{
							"name": "sort1"
						}
					],
					"scriptLines": [
						"source(output(",
						"          id as integer,",
						"          name as string,",
						"          gender as string,",
						"          salary as integer",
						"     ),",
						"     allowSchemaDrift: true,",
						"     validateSchema: false,",
						"     ignoreNoFilesFound: false) ~> source1",
						"source1 aggregate(groupBy(id,",
						"          name,",
						"          gender,",
						"          salary),",
						"     cat = count()) ~> aggregate1",
						"aggregate1 select(mapColumn(",
						"          id,",
						"          name,",
						"          gender,",
						"          salary",
						"     ),",
						"     skipDuplicateMapInputs: true,",
						"     skipDuplicateMapOutputs: true) ~> select1",
						"select1 sort(asc(id, true)) ~> sort1",
						"sort1 sink(allowSchemaDrift: true,",
						"     validateSchema: false,",
						"     input(",
						"          {Sale Key} as string,",
						"          {Invoice Date Key} as string,",
						"          {Delivery Date Key} as string,",
						"          Quantity as string,",
						"          {Unit Price} as string,",
						"          {Tax Rate} as string,",
						"          {Total Excluding Tax} as string,",
						"          Profit as string",
						"     ),",
						"     partitionFileNames:['cleaneddata.csv'],",
						"     umask: 0022,",
						"     preCommands: [],",
						"     postCommands: [],",
						"     skipDuplicateMapInputs: true,",
						"     skipDuplicateMapOutputs: true,",
						"     partitionBy('hash', 1)) ~> sink1"
					]
				}
			},
			"dependsOn": []
		},
		{
			"name": "[concat(parameters('factoryName'), '/dataflow2')]",
			"type": "Microsoft.DataFactory/factories/dataflows",
			"apiVersion": "2018-06-01",
			"properties": {
				"type": "MappingDataFlow",
				"typeProperties": {
					"sources": [
						{
							"dataset": {
								"referenceName": "ds_duplcate",
								"type": "DatasetReference"
							},
							"name": "source1"
						}
					],
					"sinks": [
						{
							"dataset": {
								"referenceName": "ds_output",
								"type": "DatasetReference"
							},
							"name": "sink1"
						}
					],
					"transformations": [
						{
							"name": "aggregate1"
						},
						{
							"name": "sort1"
						}
					],
					"scriptLines": [
						"source(output(",
						"          id as string,",
						"          name as string,",
						"          gender as string,",
						"          salary as string",
						"     ),",
						"     allowSchemaDrift: true,",
						"     validateSchema: false,",
						"     ignoreNoFilesFound: false) ~> source1",
						"source1 aggregate(groupBy(id),",
						"     name = first(name),",
						"          gender = first(gender),",
						"          salary = first(salary)) ~> aggregate1",
						"aggregate1 sort(asc(id, true)) ~> sort1",
						"sort1 sink(allowSchemaDrift: true,",
						"     validateSchema: false,",
						"     input(",
						"          {Sale Key} as string,",
						"          {Invoice Date Key} as string,",
						"          {Delivery Date Key} as string,",
						"          Quantity as string,",
						"          {Unit Price} as string,",
						"          {Tax Rate} as string,",
						"          {Total Excluding Tax} as string,",
						"          Profit as string",
						"     ),",
						"     partitionFileNames:['groupbyid.csv'],",
						"     umask: 0022,",
						"     preCommands: [],",
						"     postCommands: [],",
						"     skipDuplicateMapInputs: true,",
						"     skipDuplicateMapOutputs: true,",
						"     partitionBy('hash', 1)) ~> sink1"
					]
				}
			},
			"dependsOn": []
		},
		{
			"name": "[concat(parameters('factoryName'), '/dataflow3')]",
			"type": "Microsoft.DataFactory/factories/dataflows",
			"apiVersion": "2018-06-01",
			"properties": {
				"type": "MappingDataFlow",
				"typeProperties": {
					"sources": [
						{
							"dataset": {
								"referenceName": "ds_duplcate",
								"type": "DatasetReference"
							},
							"name": "source1"
						}
					],
					"sinks": [
						{
							"dataset": {
								"referenceName": "ds_output",
								"type": "DatasetReference"
							},
							"name": "sink1"
						}
					],
					"transformations": [
						{
							"name": "aggregate1"
						}
					],
					"scriptLines": [
						"source(output(",
						"          id as string,",
						"          name as string,",
						"          gender as string,",
						"          salary as string",
						"     ),",
						"     allowSchemaDrift: true,",
						"     validateSchema: false,",
						"     ignoreNoFilesFound: false) ~> source1",
						"source1 aggregate(groupBy(id),",
						"     name = last(name),",
						"          gender = last(gender),",
						"          salary = last(salary)) ~> aggregate1",
						"aggregate1 sink(allowSchemaDrift: true,",
						"     validateSchema: false,",
						"     input(",
						"          {Sale Key} as string,",
						"          {Invoice Date Key} as string,",
						"          {Delivery Date Key} as string,",
						"          Quantity as string,",
						"          {Unit Price} as string,",
						"          {Tax Rate} as string,",
						"          {Total Excluding Tax} as string,",
						"          Profit as string",
						"     ),",
						"     umask: 0022,",
						"     preCommands: [],",
						"     postCommands: [],",
						"     skipDuplicateMapInputs: true,",
						"     skipDuplicateMapOutputs: true) ~> sink1"
					]
				}
			},
			"dependsOn": []
		},
		{
			"name": "[concat(parameters('factoryName'), '/dataflow4')]",
			"type": "Microsoft.DataFactory/factories/dataflows",
			"apiVersion": "2018-06-01",
			"properties": {
				"type": "MappingDataFlow",
				"typeProperties": {
					"sources": [
						{
							"dataset": {
								"referenceName": "ds_cleanfilepovit",
								"type": "DatasetReference"
							},
							"name": "source1"
						}
					],
					"sinks": [
						{
							"dataset": {
								"referenceName": "ds_cleanfilepovit",
								"type": "DatasetReference"
							},
							"name": "sink1"
						}
					],
					"transformations": [
						{
							"name": "pivot1"
						},
						{
							"name": "derivedColumn1"
						}
					],
					"scriptLines": [
						"source(output(",
						"          id as integer,",
						"          name as string,",
						"          gender as string,",
						"          salary as integer",
						"     ),",
						"     allowSchemaDrift: true,",
						"     validateSchema: false,",
						"     ignoreNoFilesFound: false) ~> source1",
						"source1 pivot(groupBy(id),",
						"     pivotBy(gender, ['Female', 'Male']),",
						"     {} = count(),",
						"     columnNaming: '$N$V',",
						"     lateral: true) ~> pivot1",
						"pivot1 derive(Female = iifNull(Female, 0),",
						"          Male = iifNull(Male, 0)) ~> derivedColumn1",
						"derivedColumn1 sink(allowSchemaDrift: true,",
						"     validateSchema: false,",
						"     input(",
						"          id as string,",
						"          name as string,",
						"          gender as string,",
						"          salary as string",
						"     ),",
						"     partitionFileNames:['povitdata'],",
						"     umask: 0022,",
						"     preCommands: [],",
						"     postCommands: [],",
						"     skipDuplicateMapInputs: true,",
						"     skipDuplicateMapOutputs: true,",
						"     partitionBy('hash', 1)) ~> sink1"
					]
				}
			},
			"dependsOn": []
		},
		{
			"name": "[concat(parameters('factoryName'), '/dataflow6')]",
			"type": "Microsoft.DataFactory/factories/dataflows",
			"apiVersion": "2018-06-01",
			"properties": {
				"type": "MappingDataFlow",
				"typeProperties": {
					"sources": [
						{
							"dataset": {
								"referenceName": "ds_duplcate",
								"type": "DatasetReference"
							},
							"name": "source1"
						}
					],
					"sinks": [
						{
							"dataset": {
								"referenceName": "ds_output",
								"type": "DatasetReference"
							},
							"name": "sink1"
						}
					],
					"transformations": [
						{
							"name": "alterRow1"
						}
					],
					"scriptLines": [
						"source(output(",
						"          id as integer,",
						"          name as string,",
						"          gender as string,",
						"          salary as integer",
						"     ),",
						"     allowSchemaDrift: true,",
						"     validateSchema: false,",
						"     ignoreNoFilesFound: false) ~> source1",
						"source1 alterRow(deleteIf(gender=='Male')) ~> alterRow1",
						"alterRow1 sink(allowSchemaDrift: true,",
						"     validateSchema: false,",
						"     input(",
						"          {Sale Key} as string,",
						"          {Invoice Date Key} as string,",
						"          {Delivery Date Key} as string,",
						"          Quantity as string,",
						"          {Unit Price} as string,",
						"          {Tax Rate} as string,",
						"          {Total Excluding Tax} as string,",
						"          Profit as string",
						"     ),",
						"     umask: 0022,",
						"     preCommands: [],",
						"     postCommands: [],",
						"     skipDuplicateMapInputs: true,",
						"     skipDuplicateMapOutputs: true) ~> sink1"
					]
				}
			},
			"dependsOn": []
		},
		{
			"name": "[concat(parameters('factoryName'), '/dataflow7')]",
			"type": "Microsoft.DataFactory/factories/dataflows",
			"apiVersion": "2018-06-01",
			"properties": {
				"type": "MappingDataFlow",
				"typeProperties": {
					"sources": [
						{
							"dataset": {
								"referenceName": "ds_crossdata",
								"type": "DatasetReference"
							},
							"name": "source1"
						}
					],
					"sinks": [
						{
							"dataset": {
								"referenceName": "ds_cleancross",
								"type": "DatasetReference"
							},
							"name": "sink1"
						}
					],
					"transformations": [
						{
							"name": "select1"
						},
						{
							"name": "aggregate2"
						},
						{
							"name": "pyear"
						},
						{
							"name": "cyear"
						},
						{
							"name": "join1"
						},
						{
							"name": "sort1"
						},
						{
							"name": "derivedColumn1"
						}
					],
					"scriptLines": [
						"source(output(",
						"          Year as integer,",
						"          Month as string,",
						"          Amount as integer",
						"     ),",
						"     allowSchemaDrift: true,",
						"     validateSchema: false,",
						"     ignoreNoFilesFound: false) ~> source1",
						"source1 select(mapColumn(",
						"          Year,",
						"          Amount",
						"     ),",
						"     skipDuplicateMapInputs: true,",
						"     skipDuplicateMapOutputs: true) ~> select1",
						"sort1 aggregate(groupBy(Year),",
						"     tot = sum(Amount)) ~> aggregate2",
						"aggregate2 select(mapColumn(",
						"          pYear = Year,",
						"          ptot = tot",
						"     ),",
						"     skipDuplicateMapInputs: true,",
						"     skipDuplicateMapOutputs: true) ~> pyear",
						"aggregate2 select(mapColumn(",
						"          cYear = Year,",
						"          ctot = tot",
						"     ),",
						"     skipDuplicateMapInputs: true,",
						"     skipDuplicateMapOutputs: true) ~> cyear",
						"cyear, pyear join(cYear - pYear == 1,",
						"     joinType:'cross',",
						"     matchType:'exact',",
						"     ignoreSpaces: false,",
						"     broadcast: 'auto')~> join1",
						"select1 sort(asc(Year, true)) ~> sort1",
						"join1 derive(grate = concat(toString(round(((ctot - ptot) / ptot) * 100, 1)), \" %\"),",
						"          Gstate = iif(ctot>ptot, 'Increased', iif(ctot<ptot, 'Decreased', 'NoChange'))) ~> derivedColumn1",
						"derivedColumn1 sink(allowSchemaDrift: true,",
						"     validateSchema: false,",
						"     input(",
						"          {2021} as string,",
						"          {5697} as string,",
						"          {2020} as string,",
						"          {5429} as string,",
						"          {4.9 %} as string,",
						"          Increased as string",
						"     ),",
						"     partitionFileNames:['cleancrossdata.csv'],",
						"     umask: 0022,",
						"     preCommands: [],",
						"     postCommands: [],",
						"     skipDuplicateMapInputs: true,",
						"     skipDuplicateMapOutputs: true,",
						"     partitionBy('hash', 1)) ~> sink1"
					]
				}
			},
			"dependsOn": []
		},
		{
			"name": "[concat(parameters('factoryName'), '/pipeline3')]",
			"type": "Microsoft.DataFactory/factories/pipelines",
			"apiVersion": "2018-06-01",
			"properties": {
				"activities": [
					{
						"name": "Data flow1",
						"type": "ExecuteDataFlow",
						"dependsOn": [],
						"policy": {
							"timeout": "0.12:00:00",
							"retry": 0,
							"retryIntervalInSeconds": 30,
							"secureOutput": false,
							"secureInput": false
						},
						"userProperties": [],
						"typeProperties": {
							"dataflow": {
								"referenceName": "dataflow1",
								"type": "DataFlowReference",
								"parameters": {},
								"datasetParameters": {
									"source1": {},
									"sink1": {}
								}
							},
							"staging": {},
							"compute": {
								"coreCount": 8,
								"computeType": "General"
							},
							"traceLevel": "Fine"
						}
					}
				],
				"policy": {
					"elapsedTimeMetric": {}
				},
				"annotations": []
			},
			"dependsOn": [
				"[concat(variables('factoryId'), '/dataflows/dataflow1')]"
			]
		},
		{
			"name": "[concat(parameters('factoryName'), '/pipeline4')]",
			"type": "Microsoft.DataFactory/factories/pipelines",
			"apiVersion": "2018-06-01",
			"properties": {
				"activities": [
					{
						"name": "Data flow1",
						"type": "ExecuteDataFlow",
						"dependsOn": [],
						"policy": {
							"timeout": "0.12:00:00",
							"retry": 0,
							"retryIntervalInSeconds": 30,
							"secureOutput": false,
							"secureInput": false
						},
						"userProperties": [],
						"typeProperties": {
							"dataflow": {
								"referenceName": "dataflow2",
								"type": "DataFlowReference",
								"parameters": {},
								"datasetParameters": {
									"source1": {},
									"sink1": {}
								}
							},
							"staging": {},
							"compute": {
								"coreCount": 8,
								"computeType": "General"
							},
							"traceLevel": "Fine"
						}
					}
				],
				"policy": {
					"elapsedTimeMetric": {}
				},
				"annotations": []
			},
			"dependsOn": [
				"[concat(variables('factoryId'), '/dataflows/dataflow2')]"
			]
		},
		{
			"name": "[concat(parameters('factoryName'), '/pipeline7')]",
			"type": "Microsoft.DataFactory/factories/pipelines",
			"apiVersion": "2018-06-01",
			"properties": {
				"activities": [
					{
						"name": "dataflow7",
						"type": "ExecuteDataFlow",
						"dependsOn": [],
						"policy": {
							"timeout": "0.12:00:00",
							"retry": 0,
							"retryIntervalInSeconds": 30,
							"secureOutput": false,
							"secureInput": false
						},
						"userProperties": [],
						"typeProperties": {
							"dataflow": {
								"referenceName": "dataflow7",
								"type": "DataFlowReference",
								"parameters": {},
								"datasetParameters": {
									"source1": {},
									"sink1": {}
								}
							},
							"staging": {},
							"compute": {
								"coreCount": 8,
								"computeType": "General"
							},
							"traceLevel": "Fine"
						}
					}
				],
				"policy": {
					"elapsedTimeMetric": {}
				},
				"annotations": []
			},
			"dependsOn": [
				"[concat(variables('factoryId'), '/dataflows/dataflow7')]"
			]
		}
	]
}